hack4u/__init__.py
hack4u/courses.py
hack4u/utils.py
davidshack4u-0.2.0.dist-info/METADATA
davidshack4u-0.2.0.dist-info/WHEEL
davidshack4u-0.2.0.dist-info/top_level.txt
davidshack4u-0.2.0.dist-info/RECORD
