Metadata-Version: 2.1
Name: davidshack4u
Version: 0.2.0
Summary: Biblioteca para consultar cursos de hack4u.
Home-page: https://hack4u.io
Author: David Lopez
